{
    "status": "success",
    "code": "OK000",
    "result": {
        "pageNumber": 1,
        "rowsOfPage": 10,
        "total": 5,
        "data": [
            {
                "orders": [
                    {
                        "id": 153,
                        "statusId": 4,
                        "quotationSheet": "0153",
                        "fullName": "apetra",
                        "amount": "4,567.00",
                        "travelInfo": "puebla",
                        "supplier": "EUROMUNDO",
                        "reservationNumber": "xxxx8999",
                        "city": "CDMX",
                        "branch": "IZTAPALAPA",
                        "salesPerson": "Said Guerrero",
                        "orderDate": "07-03-2024",
                        "quoteStatus": "EXPIRADO",
                        "paidStatus": "PENDIENTE",
                        "contactPhoneNum": "5599899622",
                        "contactEmail": "g@g.com",
                        "emergencyContactPhone": "5599899622",
                        "emergencyContact": "pp",
                        "hasFiles": false,
                        "orderFileResponse": null,
                        "idString": "0153",
                        "amountWCommission": "4,568.00",
                        "partialPaymentNumber": 0,
                        "paymentTypeId": 1,
                        "amountBD": 4567.00,
                        "amountDue": 0
                    },
                    {
                        "id": 152,
                        "statusId": 4,
                        "quotationSheet": "0152",
                        "fullName": "juana",
                        "amount": "67,990.00",
                        "travelInfo": "puebla",
                        "supplier": "MAGNICHARTERS",
                        "reservationNumber": "45560pu",
                        "city": "CDMX",
                        "branch": "IZTAPALAPA",
                        "salesPerson": "Said Guerrero",
                        "orderDate": "07-03-2024",
                        "quoteStatus": "EXPIRADO",
                        "paidStatus": "PENDIENTE",
                        "contactPhoneNum": "5599899622",
                        "contactEmail": "g@g.com",
                        "emergencyContactPhone": "5599899622",
                        "emergencyContact": "pp",
                        "hasFiles": false,
                        "orderFileResponse": null,
                        "idString": "0152",
                        "amountWCommission": "67,990.00",
                        "partialPaymentNumber": 3,
                        "paymentTypeId": 1,
                        "amountBD": 67990.00,
                        "amountDue": 20000.00
                    },
                    {
                        "id": 150,
                        "statusId": 4,
                        "quotationSheet": "0150",
                        "fullName": "prueba said",
                        "amount": "5,000.00",
                        "travelInfo": "Viaje a cancun",
                        "supplier": "MAGNICHARTERS",
                        "reservationNumber": "x-00987ei",
                        "city": "COAHUILA",
                        "branch": "NORTE",
                        "salesPerson": "Said Guerrero",
                        "orderDate": "05-03-2024",
                        "quoteStatus": "EXPIRADO",
                        "paidStatus": "PENDIENTE",
                        "contactPhoneNum": "4455667786",
                        "contactEmail": "s@s.com",
                        "emergencyContactPhone": "4455667788",
                        "emergencyContact": "pp",
                        "hasFiles": false,
                        "orderFileResponse": null,
                        "idString": "0150",
                        "amountWCommission": "5,000.00",
                        "partialPaymentNumber": 4,
                        "paymentTypeId": 1,
                        "amountBD": 5000.00,
                        "amountDue": 749.50
                    },
                    {
                        "id": 149,
                        "statusId": 4,
                        "quotationSheet": "0149",
                        "fullName": "prueba said",
                        "amount": "5,000.00",
                        "travelInfo": "Viaje a cancun",
                        "supplier": "MAGNICHARTERS",
                        "reservationNumber": "x-00987ee",
                        "city": "CHIAPAS",
                        "branch": "NORTE",
                        "salesPerson": "Said Guerrero",
                        "orderDate": "05-03-2024",
                        "quoteStatus": "EXPIRADO",
                        "paidStatus": "PENDIENTE",
                        "contactPhoneNum": "4455667786",
                        "contactEmail": "s@s.com",
                        "emergencyContactPhone": "4455667788",
                        "emergencyContact": "pp",
                        "hasFiles": false,
                        "orderFileResponse": null,
                        "idString": "0149",
                        "amountWCommission": "5,000.00",
                        "partialPaymentNumber": 0,
                        "paymentTypeId": 1,
                        "amountBD": 5000.00,
                        "amountDue": 0
                    },
                    {
                        "id": 147,
                        "statusId": 4,
                        "quotationSheet": "0147",
                        "fullName": "prueba said",
                        "amount": "5,000.00",
                        "travelInfo": "Viaje a cancun",
                        "supplier": "MAGNICHARTERS",
                        "reservationNumber": "x-00987",
                        "city": "CHIAPAS",
                        "branch": "NORTE",
                        "salesPerson": "Said Guerrero",
                        "orderDate": "05-03-2024",
                        "quoteStatus": "EXPIRADO",
                        "paidStatus": "PENDIENTE",
                        "contactPhoneNum": "4455667786",
                        "contactEmail": "s@s.com",
                        "emergencyContactPhone": "4455667788",
                        "emergencyContact": "pp",
                        "hasFiles": false,
                        "orderFileResponse": null,
                        "idString": "0147",
                        "amountWCommission": "5,000.00",
                        "partialPaymentNumber": 0,
                        "paymentTypeId": 1,
                        "amountBD": 5000.00,
                        "amountDue": 0
                    }
                ],
                "dollar": "18.99",
                "euro": "19.22"
            }
        ]
    },
    "httpCode": "OK",
    "error": null
}